AUTHORS.rst
CONTRIBUTING.rst
HISTORY.rst
LICENSE
MANIFEST.in
README.rst
setup.cfg
setup.py
docs/Makefile
docs/authors.rst
docs/conf.py
docs/contributing.rst
docs/history.rst
docs/index.rst
docs/installation.rst
docs/make.bat
docs/readme.rst
docs/usage.rst
excelasyn/__init__.py
excelasyn/cli.py
excelasyn/excelasyn.py
excelasyn.egg-info/PKG-INFO
excelasyn.egg-info/SOURCES.txt
excelasyn.egg-info/dependency_links.txt
excelasyn.egg-info/entry_points.txt
excelasyn.egg-info/not-zip-safe
excelasyn.egg-info/requires.txt
excelasyn.egg-info/top_level.txt
tests/test_excelasyn.py