Metadata-Version: 1.1
Name: excelasyn
Version: 1.0.0
Summary: libreria para armar excel con librerias asincronas 
Home-page: https://github.com/alex-12-04@hotmail.com/excelasyn
Author: alexander grajales
Author-email: alex-12-04@hotmail.com
License: MIT license
Keywords: excelasyn
Platform: UNKNOWN
Classifier: Development Status :: 2 - Pre-Alpha
Classifier: Intended Audience :: Developers
Classifier: License :: OSI Approved :: MIT License
Classifier: Natural Language :: English
Classifier: Programming Language :: Python :: 2
Classifier: Programming Language :: Python :: 2.7
Classifier: Programming Language :: Python :: 3
Classifier: Programming Language :: Python :: 3.4
Classifier: Programming Language :: Python :: 3.5
Classifier: Programming Language :: Python :: 3.6
